hit_table_helper/__init__.py
hit_table_helper/course_mask.py
hit_table_helper/course_set.py
hit_table_helper/hit_api_io.py
hit_table_helper/id_generators.py
hit_table_helper-1.3.dist-info/LICENSE
hit_table_helper-1.3.dist-info/METADATA
hit_table_helper-1.3.dist-info/WHEEL
hit_table_helper-1.3.dist-info/top_level.txt
hit_table_helper-1.3.dist-info/RECORD
