Metadata-Version: 2.1
Name: hit-table-helper
Version: 1.3
Summary: Course table helper for Harbin Institute of Technology.
Home-page: https://git.hit.edu.cn/Chemie13/hit-table-helper
Author: Y.C. Long
Author-email: 847072154@qq.com
License: MIT
Keywords: chemistry,analytical chemistry
Platform: UNKNOWN
Classifier: Development Status :: 2 - Pre-Alpha
Classifier: Intended Audience :: Developers
Classifier: License :: OSI Approved :: MIT License
Classifier: Natural Language :: Chinese (Simplified)
Classifier: Natural Language :: English
Classifier: Operating System :: MacOS
Classifier: Operating System :: Microsoft :: Windows
Classifier: Operating System :: POSIX :: Linux
Classifier: Programming Language :: Python :: 3
Classifier: Programming Language :: Python :: 3.5
Classifier: Programming Language :: Python :: 3.6
Classifier: Programming Language :: Python :: 3.7
Classifier: Programming Language :: Python :: 3.8
Classifier: Programming Language :: Python :: 3 :: Only
Classifier: Topic :: Utilities
Requires-Python: >=3.8, <4
License-File: LICENSE
Requires-Dist: numpy (>=1.20.0)
Requires-Dist: pandas (>=1.3.2)
Requires-Dist: requests (>=2.26.0)
Requires-Dist: grequests (>=0.6.0)
